.gitignore
.travis.yml
README.md
pylintrc
requirements.txt
runtests.py
setup.py
test_requirements.txt
tox.ini
django_loaddata_stdin/__init__.py
django_loaddata_stdin.egg-info/PKG-INFO
django_loaddata_stdin.egg-info/SOURCES.txt
django_loaddata_stdin.egg-info/dependency_links.txt
django_loaddata_stdin.egg-info/requires.txt
django_loaddata_stdin.egg-info/top_level.txt
django_loaddata_stdin/management/__init__.py
django_loaddata_stdin/management/commands/__init__.py
django_loaddata_stdin/management/commands/loaddata.py
django_loaddata_stdin/tests/__init__.py
django_loaddata_stdin/tests/settings.py
django_loaddata_stdin/tests/test_command.py
django_loaddata_stdin/tests/testapp/__init__.py
django_loaddata_stdin/tests/testapp/models.py
django_loaddata_stdin/tests/testapp/urls.py