Metadata-Version: 1.1
Name: django-loaddata-stdin
Version: 0.1.0
Summary: Django module to load data from stdin
Home-page: https://github.com/squareweave/django-loaddata-stdin
Author: Squareweave
Author-email: team@squareweave.com.au
License: BSD
Platform: UNKNOWN
Classifier: Development Status :: 4 - Beta
Classifier: Intended Audience :: Developers
Classifier: Programming Language :: Python :: 2
Classifier: Programming Language :: Python :: 2.7
Classifier: Programming Language :: Python :: 3
Classifier: Programming Language :: Python :: 3.3
Classifier: Programming Language :: Python :: 3.4
Classifier: Programming Language :: Python :: 3.5
